{
  "version": "0.2",
  "language": "en,es",
  "words": [
    "Aceptar",
    "azordev",
    "Codacy",
    "configurated",
    "envío",
    "herokuapp",
    "vamos",
    "linkedin",
    "noopener",
    "noreferrer",
    "quickstart",
    "Revisemos",
    "Splitted",
    "timestamptz",
    "viene",
    "camelcase",
    "Recoja",
    "llegada",
    "camino",
    "estimado",
    "Tiempo",
    "Celular",
    "Nombre",
    "recepción",
    "Confirma",
    "nosotros",
    "confiar",
    "Gracias",
    "Compartirla",
    "puedes",
    "deseas",
    "esta",
    "propina",
    "experiencia",
    "finalizar",
    "datos",
    "inserta",
    "terminado",
    "Hemos",
    "ingresa",
    "pedido",
    "boleta",
    "Confirmar",
    "Celular",
    "Hola",
    "llegado",
    "ingresando",
    "proceso",
    "olvides",
    "recibir",
    "Entendido",
    "existe",
    "Atrás",
    "número",
    "Repartidor",
    "aquí",
    "paquete",
    "xsmall",
    "xlarge",
    "nocheck",
    "jsdoc",
    "entregado",
    "sido",
    "confirmado",
    "rechazado",
    "Listo",
    "salir",
    "encuentra",
    "listo",
    "Recolectado",
    "recogido",
    "Destino",
    "alcanzado",
    "Dasherlive",
    "RUT",
    "coinciden",
    "folderstructure",
    "styledcomponents",
    "issuenumber",
    "Laguan",
    "Peña",
    "Azócar",
    "Tarco",
    "Ildebrando",
    "Quinchoa",
    "Osuna",
    "jhernandez"
  ],
  "flagWords": [],
  "ignorePaths": [
    "./.github/**",
    "./.vscode/**",
    "node_modules/**",
    "public/**",
    "src/service-worker.js",
    "src/serviceWorkerRegistration.js",
    "src/reportWebVitals.js",
    "package.json",
    "package-lock.json",
    "yarn.lock",
    "README.md"
  ]
}
